slack_releaser/__init__.py
slack_releaser/exceptions.py
slack_releaser/releaser.py
slack_releaser-0.0.5.dist-info/DESCRIPTION.rst
slack_releaser-0.0.5.dist-info/METADATA
slack_releaser-0.0.5.dist-info/RECORD
slack_releaser-0.0.5.dist-info/WHEEL
slack_releaser-0.0.5.dist-info/metadata.json
slack_releaser-0.0.5.dist-info/top_level.txt
