Metadata-Version: 2.0
Name: slack-releaser
Version: 0.0.5
Summary: A zest.releaser plugin for posting changelogs to Slack
Home-page: https://github.com/mypebble/slack-releaser
Author: Pebble
Author-email: sysadmin@mypebble.co.uk
License: MIT
Platform: UNKNOWN
Requires-Dist: zest.releaser
Requires-Dist: requests
Requires-Dist: six
